mspro_python/__init__.py
mspro_python/cli.py
mspro_python/template/.DS_Store
mspro_python/template/mspro_project/.DS_Store
mspro_python/template/mspro_project/.env.example
mspro_python/template/mspro_project/.gitlab-ci.yml.example
mspro_python/template/mspro_project/alembic.ini
mspro_python/template/mspro_project/manage.sh
mspro_python/template/mspro_project/module_generator.py
mspro_python/template/mspro_project/requirements.txt
mspro_python/template/mspro_project/test_main.http
mspro_python/template/mspro_project/alembic/README
mspro_python/template/mspro_project/alembic/env.py
mspro_python/template/mspro_project/alembic/script.py.mako
mspro_python/template/mspro_project/app/.DS_Store
mspro_python/template/mspro_project/app/__init__.py
mspro_python/template/mspro_project/app/main.py
mspro_python/template/mspro_project/app/__pycache__/__init__.cpython-312.pyc
mspro_python/template/mspro_project/app/__pycache__/main.cpython-312.pyc
mspro_python/template/mspro_project/app/crud/__init__.py
mspro_python/template/mspro_project/app/crud/refresh_token.py
mspro_python/template/mspro_project/app/crud/user.py
mspro_python/template/mspro_project/app/crud/__pycache__/__init__.cpython-312.pyc
mspro_python/template/mspro_project/app/crud/__pycache__/refresh_token.cpython-312.pyc
mspro_python/template/mspro_project/app/crud/__pycache__/user.cpython-312.pyc
mspro_python/template/mspro_project/app/models/__init__.py
mspro_python/template/mspro_project/app/models/refresh_token.py
mspro_python/template/mspro_project/app/models/timestamp.py
mspro_python/template/mspro_project/app/models/user.py
mspro_python/template/mspro_project/app/models/__pycache__/__init__.cpython-312.pyc
mspro_python/template/mspro_project/app/models/__pycache__/refresh_token.cpython-312.pyc
mspro_python/template/mspro_project/app/models/__pycache__/timestamp.cpython-312.pyc
mspro_python/template/mspro_project/app/models/__pycache__/user.cpython-312.pyc
mspro_python/template/mspro_project/app/routes/__init__.py
mspro_python-0.1.6.dist-info/METADATA
mspro_python-0.1.6.dist-info/WHEEL
mspro_python-0.1.6.dist-info/entry_points.txt
mspro_python-0.1.6.dist-info/top_level.txt
mspro_python-0.1.6.dist-info/RECORD
